fsdk/__init__.py
fsdkapi-0.0.5.dist-info/METADATA
fsdkapi-0.0.5.dist-info/WHEEL
fsdkapi-0.0.5.dist-info/top_level.txt
fsdkapi-0.0.5.dist-info/RECORD
