Metadata-Version: 2.1
Name: fsdkapi
Version: 0.0.5
Summary: Fsdk project API
Home-page: UNKNOWN
Author: layerqa
Author-email: usfvouhd@gmail.com
License: UNKNOWN
Platform: UNKNOWN
Classifier: Programming Language :: Python :: 3
Classifier: License :: OSI Approved :: MIT License
Classifier: Operating System :: OS Independent
Requires-Python: >=3.7
